{"cameraMode":{"drawMode":0,"name":"Shaded","section":"Shading Mode"},"sceneLighting":false,"audioPlay":false,"sceneViewState":{"m_AlwaysRefresh":false,"showFog":true,"showSkybox":false,"showFlares":true,"showImageEffects":true,"showParticleSystems":true,"showVisualEffectGraphs":true,"m_FxEnabled":true},"in2DMode":false,"pivot":{"x":4.529958724975586,"y":-2.8367490768432619,"z":-2.195518970489502},"rotation":{"x":-0.0993749350309372,"y":-0.8695995807647705,"z":0.19519881904125215,"w":-0.4427044093608856},"size":5.439760208129883,"orthographic":false}